gmdh/__init__.py
gmdh/_gmdh_core.cpython-311-x86_64-linux-gnu.so
gmdh/gmdh.py
gmdh/version.py
gmdh-1.0.3.dist-info/LICENSE.md
gmdh-1.0.3.dist-info/METADATA
gmdh-1.0.3.dist-info/WHEEL
gmdh-1.0.3.dist-info/top_level.txt
gmdh-1.0.3.dist-info/RECORD
