Metadata-Version: 2.1
Name: gmdh
Version: 1.0.3
Summary: README.md
Home-page: https://github.com/bauman-team/GMDH
Author: Artem Babin
Author-email: artem031201@gmail.com
License: LICENSE.md
Project-URL: Documentation, https://bauman-team.github.io/GMDH/python/html/
Project-URL: GMDH book, https://bauman-team.github.io/GMDH_book
Project-URL: Source Code, https://github.com/bauman-team/GMDH
Classifier: Intended Audience :: Science/Research
Classifier: Intended Audience :: Developers
Classifier: Intended Audience :: Education
Classifier: Intended Audience :: Information Technology
Classifier: Operating System :: Microsoft :: Windows
Classifier: Operating System :: Unix
Classifier: License :: OSI Approved :: Apache Software License
Classifier: Programming Language :: C++
Classifier: Programming Language :: Python :: 3.6
Classifier: Programming Language :: Python :: 3.7
Classifier: Programming Language :: Python :: 3.8
Classifier: Programming Language :: Python :: 3.9
Classifier: Programming Language :: Python :: 3.10
Classifier: Programming Language :: Python :: 3.11
Classifier: Topic :: Scientific/Engineering :: Artificial Intelligence
Classifier: Topic :: Scientific/Engineering :: Information Analysis
Requires-Python: >=3.6
License-File: LICENSE.md
Requires-Dist: docstring-inheritance
Requires-Dist: numpy
